{
	"song": {
		"player1": "bf",
		"player2": "cosmicm",
		"notes": [
			{
				"lengthInSteps": 16,
				"sectionNotes": [],
				"mustHitSection": false
			},
			{
				"lengthInSteps": 16,
				"sectionNotes": [],
				"mustHitSection": true
			},
			{
				"lengthInSteps": 16,
				"sectionNotes": [
					[
						4071.42857142857,
						1,
						214.285714285714
					],
					[
						4285.71428571429,
						2,
						321.428571428571
					],
					[
						4714.28571428571,
						0,
						214.285714285714
					],
					[
						4714.28571428571,
						3,
						214.285714285714
					]
				],
				"mustHitSection": false
			},
			{
				"lengthInSteps": 16,
				"sectionNotes": [
					[
						5142.85714285714,
						0,
						214.285714285714
					],
					[
						5142.85714285714,
						3,
						214.285714285714
					],
					[
						5464.28571428571,
						0,
						107.142857142857
					],
					[
						5464.28571428571,
						3,
						107.142857142857
					],
					[
						5785.71428571429,
						0,
						214.285714285714
					],
					[
						5785.71428571429,
						3,
						214.285714285714
					]
				],
				"mustHitSection": false
			},
			{
				"lengthInSteps": 16,
				"sectionNotes": [
					[
						6857.14285714286,
						1,
						107.142857142857
					],
					[
						7071.42857142857,
						2,
						107.142857142857
					],
					[
						7285.71428571429,
						3,
						0
					],
					[
						7392.85714285714,
						2,
						0
					],
					[
						7500,
						0,
						107.142857142857
					],
					[
						7714.28571428571,
						1,
						107.142857142857
					],
					[
						7928.57142857143,
						2,
						107.142857142857
					],
					[
						8142.85714285714,
						1,
						0
					],
					[
						8250,
						0,
						0
					],
					[
						8357.14285714286,
						3,
						107.142857142857
					]
				],
				"mustHitSection": false
			},
			{
				"lengthInSteps": 16,
				"sectionNotes": [
					[
						8571.42857142857,
						2,
						0
					],
					[
						8678.57142857143,
						1,
						0
					],
					[
						8785.71428571428,
						0,
						0
					],
					[
						8892.85714285714,
						2,
						0
					],
					[
						9000,
						3,
						0
					],
					[
						9107.14285714286,
						1,
						0
					],
					[
						9428.57142857143,
						0,
						214.285714285714
					],
					[
						9214.28571428571,
						3,
						107.142857142857
					],
					[
						10178.5714285714,
						0,
						0
					],
					[
						10071.4285714286,
						0,
						0
					],
					[
						9750,
						0,
						214.285714285714
					]
				],
				"mustHitSection": false
			},
			{
				"lengthInSteps": 16,
				"sectionNotes": [
					[
						10285.7142857143,
						1,
						107.142857142857
					],
					[
						10500,
						2,
						107.142857142857
					],
					[
						10714.2857142857,
						3,
						0
					],
					[
						10821.4285714286,
						2,
						0
					],
					[
						10928.5714285714,
						0,
						107.142857142857
					],
					[
						11142.8571428571,
						1,
						107.142857142857
					],
					[
						11357.1428571429,
						2,
						107.142857142857
					],
					[
						11571.4285714286,
						1,
						0
					],
					[
						11678.5714285714,
						0,
						0
					],
					[
						11785.7142857143,
						3,
						107.142857142857
					]
				],
				"mustHitSection": true
			},
			{
				"lengthInSteps": 16,
				"sectionNotes": [
					[
						12000,
						2,
						0
					],
					[
						12107.1428571429,
						1,
						0
					],
					[
						12214.2857142857,
						0,
						0
					],
					[
						12321.4285714286,
						2,
						0
					],
					[
						12428.5714285714,
						3,
						0
					],
					[
						12535.7142857143,
						1,
						0
					],
					[
						12857.1428571429,
						0,
						214.285714285714
					],
					[
						12642.8571428571,
						3,
						107.142857142857
					],
					[
						13178.5714285714,
						1,
						214.285714285714
					],
					[
						13607.1428571429,
						2,
						0
					],
					[
						13500,
						3,
						0
					]
				],
				"mustHitSection": true
			},
			{
				"lengthInSteps": 16,
				"sectionNotes": [
					[
						13714.2857142857,
						1,
						107.142857142857
					],
					[
						13928.5714285714,
						0,
						107.142857142857
					],
					[
						14142.8571428571,
						2,
						107.142857142857
					],
					[
						14464.2857142857,
						3,
						0
					],
					[
						14571.4285714286,
						1,
						0
					],
					[
						14785.7142857143,
						1,
						0
					],
					[
						15000,
						1,
						107.142857142857
					],
					[
						15214.2857142857,
						2,
						107.142857142857
					],
					[
						13714.2857142857,
						5,
						750
					],
					[
						14571.4285714286,
						7,
						750
					]
				],
				"mustHitSection": false
			},
			{
				"lengthInSteps": 16,
				"sectionNotes": [
					[
						15428.5714285714,
						4,
						0
					],
					[
						15857.1428571429,
						6,
						0
					],
					[
						15642.8571428571,
						7,
						107.142857142857
					],
					[
						16392.8571428571,
						4,
						0
					],
					[
						16928.5714285714,
						7,
						0
					],
					[
						17035.7142857143,
						6,
						0
					],
					[
						15428.5714285714,
						0,
						750
					],
					[
						16285.7142857143,
						1,
						750
					],
					[
						15500,
						5,
						0
					],
					[
						15571.4285714286,
						6,
						0
					],
					[
						15928.5714285714,
						5,
						0
					],
					[
						15964.2857142857,
						7,
						0
					],
					[
						16071.4285714286,
						4,
						107.142857142857
					],
					[
						16464.2857142857,
						5,
						0
					],
					[
						16535.7142857143,
						6,
						0
					],
					[
						16607.1428571429,
						5,
						0
					],
					[
						16678.5714285714,
						4,
						0
					],
					[
						16714.2857142857,
						6,
						107.142857142857
					]
				],
				"mustHitSection": true
			},
			{
				"lengthInSteps": 16,
				"sectionNotes": [
					[
						17142.8571428571,
						1,
						0
					],
					[
						17250,
						2,
						107.142857142857
					],
					[
						17464.2857142857,
						3,
						107.142857142857
					],
					[
						17678.5714285714,
						1,
						107.142857142857
					],
					[
						17892.8571428571,
						2,
						107.142857142857
					],
					[
						18321.4285714286,
						0,
						53.5714285714286
					],
					[
						18428.5714285714,
						1,
						107.142857142857
					],
					[
						18642.8571428571,
						2,
						107.142857142857
					],
					[
						18107.1428571429,
						0,
						53.5714285714286
					],
					[
						17142.8571428571,
						6,
						750
					],
					[
						18000,
						7,
						750
					]
				],
				"mustHitSection": false
			},
			{
				"lengthInSteps": 16,
				"sectionNotes": [
					[
						18857.1428571429,
						1,
						750
					],
					[
						19714.2857142857,
						2,
						321.428571428571
					],
					[
						20142.8571428571,
						1,
						107.142857142857
					],
					[
						20357.1428571429,
						0,
						107.142857142857
					],
					[
						18857.1428571429,
						4,
						0
					],
					[
						19071.4285714286,
						6,
						107.142857142857
					],
					[
						19285.7142857143,
						7,
						0
					],
					[
						19821.4285714286,
						5,
						0
					],
					[
						19928.5714285714,
						6,
						0
					],
					[
						20035.7142857143,
						7,
						0
					],
					[
						20250,
						4,
						0
					],
					[
						20357.1428571429,
						5,
						0
					],
					[
						20464.2857142857,
						6,
						0
					],
					[
						19714.2857142857,
						7,
						0
					],
					[
						18928.5714285714,
						6,
						0
					],
					[
						19000,
						5,
						0
					],
					[
						19357.1428571429,
						5,
						0
					],
					[
						19428.5714285714,
						4,
						214.285714285714
					],
					[
						20107.1428571429,
						6,
						0
					],
					[
						20178.5714285714,
						7,
						0
					]
				],
				"mustHitSection": true
			},
			{
				"lengthInSteps": 16,
				"sectionNotes": [
					[
						20571.4285714286,
						1,
						750
					],
					[
						21428.5714285714,
						3,
						750
					],
					[
						20571.4285714286,
						6,
						0
					],
					[
						20678.5714285714,
						7,
						0
					],
					[
						20785.7142857143,
						5,
						107.142857142857
					],
					[
						21107.1428571429,
						6,
						214.285714285714
					],
					[
						21428.5714285714,
						5,
						321.428571428571
					],
					[
						21857.1428571429,
						4,
						107.142857142857
					],
					[
						22071.4285714286,
						6,
						107.142857142857
					]
				],
				"mustHitSection": false
			},
			{
				"lengthInSteps": 16,
				"sectionNotes": [
					[
						22285.7142857143,
						0,
						750
					],
					[
						23142.8571428571,
						1,
						750
					],
					[
						22500,
						7,
						107.142857142857
					],
					[
						22285.7142857143,
						4,
						0
					],
					[
						22714.2857142857,
						6,
						107.142857142857
					],
					[
						22928.5714285714,
						5,
						0
					],
					[
						23250,
						7,
						0
					],
					[
						23357.1428571429,
						6,
						0
					],
					[
						23142.8571428571,
						6,
						0
					],
					[
						23785.7142857143,
						4,
						107.142857142857
					],
					[
						22357.1428571429,
						6,
						0
					],
					[
						22428.5714285714,
						5,
						0
					],
					[
						23000,
						4,
						0
					],
					[
						23428.5714285714,
						5,
						0
					],
					[
						23500,
						6,
						0
					],
					[
						23571.4285714286,
						5,
						0
					],
					[
						23642.8571428571,
						6,
						0
					],
					[
						23714.2857142857,
						7,
						107.142857142857
					]
				],
				"mustHitSection": false
			},
			{
				"lengthInSteps": 16,
				"sectionNotes": [
					[
						24000,
						2,
						750
					],
					[
						24857.1428571429,
						3,
						750
					],
					[
						24000,
						6,
						107.142857142857
					],
					[
						24214.2857142857,
						7,
						107.142857142857
					],
					[
						24428.5714285714,
						6,
						321.428571428571
					],
					[
						24857.1428571429,
						5,
						0
					],
					[
						25071.4285714286,
						5,
						0
					],
					[
						25285.7142857143,
						7,
						107.142857142857
					],
					[
						25500,
						5,
						107.142857142857
					]
				],
				"mustHitSection": false
			},
			{
				"lengthInSteps": 16,
				"sectionNotes": [
					[
						25714.2857142857,
						5,
						750
					],
					[
						26571.4285714286,
						6,
						321.428571428571
					],
					[
						27000,
						5,
						107.142857142857
					],
					[
						27214.2857142857,
						4,
						107.142857142857
					],
					[
						25714.2857142857,
						0,
						0
					],
					[
						25821.4285714286,
						1,
						0
					],
					[
						25928.5714285714,
						2,
						107.142857142857
					],
					[
						26571.4285714286,
						1,
						107.142857142857
					],
					[
						26785.7142857143,
						3,
						0
					],
					[
						27000,
						0,
						107.142857142857
					],
					[
						27214.2857142857,
						3,
						107.142857142857
					],
					[
						25750,
						2,
						0
					],
					[
						26285.7142857143,
						2,
						0
					],
					[
						26357.1428571429,
						0,
						107.142857142857
					],
					[
						26857.1428571429,
						2,
						107.142857142857
					],
					[
						26142.8571428571,
						3,
						0
					]
				],
				"mustHitSection": true
			},
			{
				"lengthInSteps": 16,
				"sectionNotes": [
					[
						27428.5714285714,
						1,
						107.142857142857
					],
					[
						27642.8571428571,
						2,
						107.142857142857
					],
					[
						27857.1428571429,
						1,
						107.142857142857
					],
					[
						28178.5714285714,
						0,
						160.714285714286
					],
					[
						28500,
						2,
						160.714285714286
					],
					[
						28714.2857142857,
						1,
						107.142857142857
					],
					[
						28928.5714285714,
						2,
						107.142857142857
					],
					[
						27428.5714285714,
						5,
						321.428571428571
					],
					[
						27857.1428571429,
						7,
						321.428571428571
					],
					[
						28285.7142857143,
						6,
						428.571428571429
					]
				],
				"mustHitSection": false
			},
			{
				"lengthInSteps": 16,
				"sectionNotes": [
					[
						29142.8571428571,
						3,
						321.428571428571
					],
					[
						29571.4285714286,
						1,
						321.428571428571
					],
					[
						30000,
						0,
						535.714285714286
					],
					[
						29142.8571428571,
						7,
						0
					],
					[
						29357.1428571429,
						4,
						107.142857142857
					],
					[
						29571.4285714286,
						5,
						0
					],
					[
						29678.5714285714,
						6,
						0
					],
					[
						29785.7142857143,
						4,
						107.142857142857
					],
					[
						30000,
						5,
						107.142857142857
					],
					[
						30214.2857142857,
						6,
						0
					],
					[
						30642.8571428571,
						4,
						107.142857142857
					],
					[
						29214.2857142857,
						6,
						0
					],
					[
						29285.7142857143,
						5,
						0
					],
					[
						30285.7142857143,
						7,
						0
					],
					[
						30357.1428571429,
						6,
						0
					],
					[
						30428.5714285714,
						5,
						107.142857142857
					]
				],
				"mustHitSection": false
			},
			{
				"lengthInSteps": 16,
				"sectionNotes": [
					[
						30857.1428571429,
						1,
						0
					],
					[
						30964.2857142857,
						0,
						0
					],
					[
						31071.4285714286,
						1,
						107.142857142857
					],
					[
						31392.8571428571,
						1,
						0
					],
					[
						31607.1428571429,
						1,
						0
					],
					[
						31821.4285714286,
						3,
						53.5714285714286
					],
					[
						32035.7142857143,
						3,
						53.5714285714286
					],
					[
						32250,
						0,
						53.5714285714286
					],
					[
						32464.2857142857,
						0,
						53.5714285714286
					],
					[
						30857.1428571429,
						5,
						0
					],
					[
						30964.2857142857,
						4,
						0
					],
					[
						30964.2857142857,
						0,
						0
					],
					[
						31071.4285714286,
						5,
						107.142857142857
					],
					[
						31071.4285714286,
						1,
						0
					],
					[
						31285.7142857143,
						6,
						321.428571428571
					],
					[
						31714.2857142857,
						5,
						321.428571428571
					],
					[
						32142.8571428571,
						4,
						321.428571428571
					]
				],
				"mustHitSection": false
			},
			{
				"lengthInSteps": 16,
				"sectionNotes": [
					[
						32571.4285714286,
						5,
						0
					],
					[
						32571.4285714286,
						1,
						0
					],
					[
						32678.5714285714,
						4,
						0
					],
					[
						32678.5714285714,
						0,
						0
					],
					[
						32785.7142857143,
						6,
						107.142857142857
					],
					[
						32785.7142857143,
						2,
						107.142857142857
					],
					[
						33000,
						3,
						0
					],
					[
						33000,
						7,
						0
					],
					[
						33107.1428571428,
						2,
						0
					],
					[
						33107.1428571428,
						6,
						0
					],
					[
						33214.2857142857,
						1,
						107.142857142857
					],
					[
						33214.2857142857,
						5,
						107.142857142857
					],
					[
						33428.5714285714,
						0,
						0
					],
					[
						33535.7142857143,
						2,
						0
					],
					[
						33428.5714285714,
						4,
						0
					],
					[
						33535.7142857143,
						6,
						0
					],
					[
						33642.8571428571,
						5,
						0
					],
					[
						33642.8571428571,
						1,
						0
					],
					[
						33750,
						2,
						107.142857142857
					],
					[
						33750,
						6,
						107.142857142857
					],
					[
						33964.2857142857,
						5,
						0
					],
					[
						34071.4285714286,
						4,
						0
					],
					[
						33964.2857142857,
						1,
						0
					],
					[
						34071.4285714286,
						0,
						0
					],
					[
						34178.5714285714,
						2,
						107.142857142857
					],
					[
						34178.5714285714,
						6,
						107.142857142857
					],
					[
						32642.8571428571,
						2,
						0
					],
					[
						32642.8571428571,
						6,
						0
					],
					[
						33071.4285714286,
						0,
						0
					],
					[
						33071.4285714286,
						4,
						0
					],
					[
						33714.2857142857,
						0,
						0
					],
					[
						33714.2857142857,
						4,
						0
					]
				],
				"mustHitSection": true
			},
			{
				"lengthInSteps": 16,
				"sectionNotes": [],
				"mustHitSection": false
			},
			{
				"lengthInSteps": 16,
				"sectionNotes": [],
				"mustHitSection": false
			},
			{
				"lengthInSteps": 16,
				"sectionNotes": [],
				"mustHitSection": true
			},
			{
				"lengthInSteps": 16,
				"sectionNotes": [
					[
						40178.5714285714,
						1,
						107.142857142857
					],
					[
						40392.8571428572,
						2,
						535.714285714286
					],
					[
						40392.8571428572,
						0,
						535.714285714286
					]
				],
				"mustHitSection": false
			},
			{
				"lengthInSteps": 16,
				"sectionNotes": [
					[
						41142.8571428572,
						1,
						321.428571428571
					],
					[
						41571.4285714286,
						2,
						321.428571428571
					],
					[
						42000,
						0,
						321.428571428571
					],
					[
						42428.5714285714,
						1,
						107.142857142857
					],
					[
						42642.8571428572,
						3,
						0
					],
					[
						42750,
						0,
						0
					]
				],
				"mustHitSection": false
			},
			{
				"lengthInSteps": 16,
				"sectionNotes": [
					[
						42857.1428571429,
						1,
						321.428571428571
					],
					[
						43285.7142857143,
						3,
						321.428571428571
					],
					[
						43714.2857142857,
						2,
						321.428571428571
					],
					[
						44142.8571428572,
						0,
						107.142857142857
					],
					[
						44357.1428571429,
						2,
						0
					],
					[
						44464.2857142857,
						3,
						0
					]
				],
				"mustHitSection": false
			},
			{
				"lengthInSteps": 16,
				"sectionNotes": [
					[
						44571.4285714286,
						1,
						321.428571428571
					],
					[
						45000,
						2,
						321.428571428571
					],
					[
						45428.5714285714,
						0,
						321.428571428571
					],
					[
						46071.4285714286,
						3,
						0
					],
					[
						46178.5714285714,
						0,
						0
					],
					[
						45857.1428571429,
						3,
						0
					],
					[
						45964.2857142857,
						1,
						0
					]
				],
				"mustHitSection": false
			},
			{
				"lengthInSteps": 16,
				"sectionNotes": [
					[
						46285.7142857143,
						1,
						321.428571428571
					],
					[
						46714.2857142857,
						3,
						321.428571428571
					],
					[
						47571.4285714286,
						2,
						107.142857142857
					],
					[
						47785.7142857143,
						0,
						0
					],
					[
						47892.8571428572,
						3,
						0
					],
					[
						47142.8571428572,
						1,
						321.428571428571
					]
				],
				"mustHitSection": false
			},
			{
				"lengthInSteps": 16,
				"sectionNotes": [
					[
						48000,
						1,
						321.428571428571
					],
					[
						48428.5714285714,
						2,
						321.428571428571
					],
					[
						48857.1428571429,
						0,
						321.428571428571
					],
					[
						49285.7142857143,
						1,
						107.142857142857
					],
					[
						49500,
						3,
						0
					],
					[
						49607.1428571429,
						0,
						0
					]
				],
				"mustHitSection": true
			},
			{
				"lengthInSteps": 16,
				"sectionNotes": [
					[
						49714.2857142857,
						1,
						321.428571428571
					],
					[
						50142.8571428572,
						3,
						321.428571428571
					],
					[
						50571.4285714286,
						2,
						321.428571428571
					],
					[
						51000,
						0,
						107.142857142857
					],
					[
						51214.2857142857,
						2,
						0
					],
					[
						51321.4285714286,
						3,
						0
					]
				],
				"mustHitSection": true
			},
			{
				"lengthInSteps": 16,
				"sectionNotes": [
					[
						51428.5714285714,
						1,
						321.428571428571
					],
					[
						51857.1428571429,
						2,
						321.428571428571
					],
					[
						52285.7142857143,
						0,
						321.428571428571
					],
					[
						52928.5714285714,
						3,
						0
					],
					[
						53035.7142857143,
						0,
						0
					],
					[
						52714.2857142857,
						3,
						0
					],
					[
						52821.4285714286,
						1,
						0
					]
				],
				"mustHitSection": true
			},
			{
				"lengthInSteps": 16,
				"sectionNotes": [
					[
						53142.8571428572,
						1,
						321.428571428571
					],
					[
						53571.4285714286,
						3,
						321.428571428571
					],
					[
						54428.5714285714,
						2,
						107.142857142857
					],
					[
						54642.8571428572,
						0,
						0
					],
					[
						54750,
						3,
						0
					],
					[
						54000,
						1,
						321.428571428571
					]
				],
				"mustHitSection": true
			},
			{
				"lengthInSteps": 16,
				"sectionNotes": [
					[
						54857.1428571429,
						1,
						642.857142857143
					]
				],
				"mustHitSection": true
			},
			{
				"lengthInSteps": 16,
				"sectionNotes": [],
				"mustHitSection": false
			},
			{
				"lengthInSteps": 16,
				"sectionNotes": [],
				"mustHitSection": true
			},
			{
				"lengthInSteps": 16,
				"sectionNotes": [],
				"mustHitSection": false
			},
			{
				"lengthInSteps": 16,
				"sectionNotes": [],
				"mustHitSection": true
			},
			{
				"lengthInSteps": 16,
				"sectionNotes": [],
				"mustHitSection": false
			},
			{
				"lengthInSteps": 16,
				"sectionNotes": [],
				"mustHitSection": true
			},
			{
				"lengthInSteps": 16,
				"sectionNotes": [],
				"mustHitSection": false
			},
			{
				"lengthInSteps": 16,
				"sectionNotes": [],
				"mustHitSection": true
			},
			{
				"lengthInSteps": 16,
				"sectionNotes": [],
				"mustHitSection": false
			},
			{
				"lengthInSteps": 16,
				"sectionNotes": [],
				"mustHitSection": true
			},
			{
				"lengthInSteps": 16,
				"sectionNotes": [
					[
						73928.5714285715,
						1,
						535.714285714286
					],
					[
						74250,
						2,
						857.142857142857
					],
					[
						75107.1428571429,
						3,
						214.285714285714
					]
				],
				"mustHitSection": false
			},
			{
				"lengthInSteps": 16,
				"sectionNotes": [
					[
						75428.5714285714,
						1,
						107.142857142857
					],
					[
						75642.8571428571,
						2,
						107.142857142857
					],
					[
						75857.1428571429,
						3,
						0
					],
					[
						75964.2857142857,
						2,
						0
					],
					[
						76071.4285714286,
						0,
						107.142857142857
					],
					[
						76285.7142857143,
						1,
						107.142857142857
					],
					[
						76500,
						2,
						107.142857142857
					],
					[
						76714.2857142857,
						1,
						0
					],
					[
						76821.4285714286,
						0,
						0
					],
					[
						76928.5714285714,
						3,
						107.142857142857
					]
				],
				"mustHitSection": false
			},
			{
				"lengthInSteps": 16,
				"sectionNotes": [
					[
						77142.8571428571,
						2,
						0
					],
					[
						77250,
						1,
						0
					],
					[
						77357.1428571429,
						0,
						0
					],
					[
						77464.2857142857,
						2,
						0
					],
					[
						77571.4285714286,
						3,
						0
					],
					[
						77678.5714285714,
						1,
						0
					],
					[
						78000,
						0,
						214.285714285714
					],
					[
						77785.7142857143,
						3,
						107.142857142857
					],
					[
						78750,
						0,
						0
					],
					[
						78642.8571428571,
						0,
						0
					],
					[
						78321.4285714286,
						0,
						214.285714285714
					]
				],
				"mustHitSection": false
			},
			{
				"lengthInSteps": 16,
				"sectionNotes": [
					[
						78857.1428571429,
						1,
						107.142857142857
					],
					[
						79071.4285714286,
						2,
						107.142857142857
					],
					[
						79285.7142857143,
						3,
						0
					],
					[
						79392.8571428571,
						2,
						0
					],
					[
						79500,
						0,
						107.142857142857
					],
					[
						79714.2857142857,
						1,
						107.142857142857
					],
					[
						79928.5714285714,
						2,
						107.142857142857
					],
					[
						80142.8571428571,
						1,
						0
					],
					[
						80250,
						0,
						0
					],
					[
						80357.1428571429,
						3,
						107.142857142857
					]
				],
				"mustHitSection": true
			},
			{
				"lengthInSteps": 16,
				"sectionNotes": [
					[
						80571.4285714286,
						2,
						0
					],
					[
						80678.5714285714,
						1,
						0
					],
					[
						80785.7142857143,
						0,
						0
					],
					[
						80892.8571428571,
						2,
						0
					],
					[
						81000,
						3,
						0
					],
					[
						81107.1428571429,
						1,
						0
					],
					[
						81428.5714285714,
						0,
						214.285714285714
					],
					[
						81214.2857142857,
						3,
						107.142857142857
					],
					[
						81750,
						0,
						214.285714285714
					],
					[
						82071.4285714286,
						2,
						0
					],
					[
						82178.5714285714,
						3,
						0
					]
				],
				"mustHitSection": true
			},
			{
				"lengthInSteps": 16,
				"sectionNotes": [
					[
						82285.7142857143,
						1,
						107.142857142857
					],
					[
						82500,
						0,
						107.142857142857
					],
					[
						82714.2857142857,
						2,
						107.142857142857
					],
					[
						83035.7142857143,
						3,
						0
					],
					[
						83142.8571428571,
						1,
						0
					],
					[
						83357.1428571428,
						1,
						0
					],
					[
						83571.4285714286,
						1,
						107.142857142857
					],
					[
						83785.7142857143,
						2,
						107.142857142857
					],
					[
						82285.7142857143,
						5,
						750
					],
					[
						83142.8571428571,
						7,
						750
					]
				],
				"mustHitSection": false
			},
			{
				"lengthInSteps": 16,
				"sectionNotes": [
					[
						84000,
						4,
						0
					],
					[
						84428.5714285714,
						6,
						0
					],
					[
						84214.2857142857,
						7,
						107.142857142857
					],
					[
						84964.2857142857,
						4,
						0
					],
					[
						85500,
						7,
						0
					],
					[
						85607.1428571428,
						6,
						0
					],
					[
						84000,
						0,
						750
					],
					[
						84857.1428571428,
						1,
						750
					],
					[
						84071.4285714286,
						5,
						0
					],
					[
						84142.8571428571,
						6,
						0
					],
					[
						84500,
						5,
						0
					],
					[
						84535.7142857143,
						7,
						0
					],
					[
						84642.8571428571,
						4,
						107.142857142857
					],
					[
						85035.7142857143,
						5,
						0
					],
					[
						85107.1428571428,
						6,
						0
					],
					[
						85178.5714285714,
						5,
						0
					],
					[
						85250,
						4,
						0
					],
					[
						85285.7142857143,
						6,
						107.142857142857
					],
					[
						85321.4285714286,
						5,
						107.142857142857
					]
				],
				"mustHitSection": true
			},
			{
				"lengthInSteps": 16,
				"sectionNotes": [
					[
						85714.2857142857,
						1,
						0
					],
					[
						85821.4285714286,
						2,
						107.142857142857
					],
					[
						86035.7142857143,
						3,
						107.142857142857
					],
					[
						86250,
						1,
						107.142857142857
					],
					[
						86464.2857142857,
						2,
						107.142857142857
					],
					[
						86892.8571428571,
						0,
						53.5714285714286
					],
					[
						87000,
						1,
						107.142857142857
					],
					[
						87214.2857142857,
						2,
						107.142857142857
					],
					[
						86678.5714285714,
						0,
						53.5714285714286
					],
					[
						85714.2857142857,
						6,
						750
					],
					[
						86571.4285714286,
						7,
						750
					]
				],
				"mustHitSection": false
			},
			{
				"lengthInSteps": 16,
				"sectionNotes": [
					[
						87428.5714285714,
						1,
						750
					],
					[
						88285.7142857143,
						2,
						321.428571428571
					],
					[
						88714.2857142857,
						1,
						107.142857142857
					],
					[
						88928.5714285714,
						0,
						107.142857142857
					],
					[
						87428.5714285714,
						4,
						0
					],
					[
						87642.8571428571,
						6,
						107.142857142857
					],
					[
						87857.1428571428,
						7,
						0
					],
					[
						88392.8571428571,
						5,
						0
					],
					[
						88500,
						6,
						0
					],
					[
						88607.1428571428,
						7,
						0
					],
					[
						88821.4285714286,
						4,
						0
					],
					[
						88928.5714285714,
						5,
						0
					],
					[
						89035.7142857143,
						6,
						0
					],
					[
						88285.7142857143,
						7,
						0
					],
					[
						87500,
						6,
						0
					],
					[
						87571.4285714286,
						5,
						0
					],
					[
						87928.5714285714,
						5,
						0
					],
					[
						88000,
						4,
						214.285714285714
					],
					[
						88678.5714285714,
						6,
						0
					],
					[
						88750,
						7,
						0
					]
				],
				"mustHitSection": true
			},
			{
				"lengthInSteps": 16,
				"sectionNotes": [
					[
						89142.8571428571,
						1,
						750
					],
					[
						90000,
						3,
						750
					],
					[
						89142.8571428571,
						6,
						0
					],
					[
						89250,
						7,
						0
					],
					[
						89357.1428571428,
						5,
						107.142857142857
					],
					[
						89678.5714285714,
						6,
						214.285714285714
					],
					[
						90000,
						5,
						321.428571428571
					],
					[
						90428.5714285714,
						4,
						107.142857142857
					],
					[
						90642.8571428571,
						6,
						107.142857142857
					]
				],
				"mustHitSection": false
			},
			{
				"lengthInSteps": 16,
				"sectionNotes": [
					[
						90857.1428571428,
						0,
						750
					],
					[
						91714.2857142857,
						1,
						750
					],
					[
						91071.4285714286,
						7,
						107.142857142857
					],
					[
						90857.1428571428,
						4,
						0
					],
					[
						91285.7142857143,
						6,
						107.142857142857
					],
					[
						91500,
						5,
						0
					],
					[
						91821.4285714286,
						7,
						0
					],
					[
						91928.5714285714,
						6,
						0
					],
					[
						91714.2857142857,
						6,
						0
					],
					[
						92357.1428571428,
						4,
						107.142857142857
					],
					[
						90928.5714285714,
						6,
						0
					],
					[
						91000,
						5,
						0
					],
					[
						91571.4285714286,
						4,
						0
					],
					[
						92000,
						5,
						0
					],
					[
						92071.4285714286,
						6,
						0
					],
					[
						92142.8571428571,
						5,
						0
					],
					[
						92285.7142857143,
						7,
						107.142857142857
					],
					[
						92214.2857142857,
						6,
						0
					]
				],
				"mustHitSection": false
			},
			{
				"lengthInSteps": 16,
				"sectionNotes": [
					[
						92571.4285714286,
						2,
						750
					],
					[
						93428.5714285714,
						3,
						750
					],
					[
						92571.4285714286,
						6,
						107.142857142857
					],
					[
						92785.7142857143,
						7,
						107.142857142857
					],
					[
						93000,
						6,
						321.428571428571
					],
					[
						93428.5714285714,
						5,
						0
					],
					[
						93642.8571428571,
						5,
						0
					],
					[
						93857.1428571428,
						7,
						107.142857142857
					],
					[
						94071.4285714286,
						5,
						107.142857142857
					]
				],
				"mustHitSection": false
			},
			{
				"lengthInSteps": 16,
				"sectionNotes": [
					[
						94285.7142857143,
						5,
						750
					],
					[
						95142.8571428571,
						6,
						321.428571428571
					],
					[
						95571.4285714286,
						5,
						107.142857142857
					],
					[
						95785.7142857143,
						4,
						107.142857142857
					],
					[
						94285.7142857143,
						0,
						0
					],
					[
						94392.8571428571,
						1,
						0
					],
					[
						94500,
						2,
						107.142857142857
					],
					[
						94714.2857142857,
						3,
						107.142857142857
					],
					[
						95142.8571428571,
						1,
						107.142857142857
					],
					[
						95357.1428571428,
						3,
						0
					],
					[
						95571.4285714286,
						0,
						107.142857142857
					],
					[
						95785.7142857143,
						3,
						107.142857142857
					],
					[
						94321.4285714286,
						2,
						0
					],
					[
						94857.1428571428,
						2,
						0
					],
					[
						94928.5714285714,
						0,
						107.142857142857
					],
					[
						95428.5714285714,
						2,
						107.142857142857
					]
				],
				"mustHitSection": true
			},
			{
				"lengthInSteps": 16,
				"sectionNotes": [
					[
						96000,
						1,
						107.142857142857
					],
					[
						96214.2857142857,
						2,
						107.142857142857
					],
					[
						96428.5714285714,
						1,
						107.142857142857
					],
					[
						96750,
						0,
						160.714285714286
					],
					[
						97071.4285714286,
						2,
						160.714285714286
					],
					[
						97285.7142857143,
						1,
						107.142857142857
					],
					[
						97500,
						2,
						107.142857142857
					],
					[
						96000,
						5,
						321.428571428571
					],
					[
						96428.5714285714,
						7,
						321.428571428571
					],
					[
						96857.1428571428,
						6,
						428.571428571429
					]
				],
				"mustHitSection": false
			},
			{
				"lengthInSteps": 16,
				"sectionNotes": [
					[
						97714.2857142857,
						5,
						321.428571428571
					],
					[
						97714.2857142857,
						0,
						0
					],
					[
						97821.4285714286,
						1,
						0
					],
					[
						97928.5714285714,
						2,
						107.142857142857
					],
					[
						98142.8571428571,
						3,
						107.142857142857
					],
					[
						98571.4285714286,
						1,
						107.142857142857
					],
					[
						98785.7142857143,
						3,
						0
					],
					[
						99107.1428571429,
						1,
						107.142857142857
					],
					[
						99214.2857142857,
						3,
						107.142857142857
					],
					[
						97750,
						2,
						0
					],
					[
						98285.7142857143,
						2,
						0
					],
					[
						98357.1428571429,
						0,
						107.142857142857
					],
					[
						98857.1428571429,
						2,
						107.142857142857
					],
					[
						98142.8571428571,
						6,
						321.428571428571
					],
					[
						98571.4285714286,
						5,
						535.714285714286
					]
				],
				"mustHitSection": true
			},
			{
				"lengthInSteps": 16,
				"sectionNotes": [
					[
						99428.5714285714,
						1,
						0
					],
					[
						99535.7142857143,
						0,
						0
					],
					[
						99642.8571428571,
						1,
						107.142857142857
					],
					[
						99964.2857142857,
						1,
						0
					],
					[
						100178.571428571,
						1,
						0
					],
					[
						100392.857142857,
						3,
						53.5714285714286
					],
					[
						100607.142857143,
						3,
						53.5714285714286
					],
					[
						100821.428571429,
						0,
						53.5714285714286
					],
					[
						101035.714285714,
						0,
						53.5714285714286
					],
					[
						99428.5714285714,
						5,
						0
					],
					[
						99535.7142857143,
						4,
						0
					],
					[
						99535.7142857143,
						0,
						0
					],
					[
						99642.8571428571,
						5,
						107.142857142857
					],
					[
						99642.8571428571,
						1,
						0
					],
					[
						99857.1428571428,
						6,
						321.428571428571
					],
					[
						100285.714285714,
						5,
						321.428571428571
					],
					[
						100714.285714286,
						4,
						321.428571428571
					]
				],
				"mustHitSection": false
			},
			{
				"lengthInSteps": 16,
				"sectionNotes": [
					[
						101142.857142857,
						5,
						0
					],
					[
						101142.857142857,
						1,
						0
					],
					[
						101250,
						4,
						0
					],
					[
						101250,
						0,
						0
					],
					[
						101357.142857143,
						6,
						107.142857142857
					],
					[
						101357.142857143,
						2,
						107.142857142857
					],
					[
						101571.428571429,
						3,
						0
					],
					[
						101571.428571429,
						7,
						0
					],
					[
						101678.571428571,
						2,
						0
					],
					[
						101678.571428571,
						6,
						0
					],
					[
						101785.714285714,
						1,
						107.142857142857
					],
					[
						101785.714285714,
						5,
						107.142857142857
					],
					[
						102000,
						0,
						0
					],
					[
						102107.142857143,
						2,
						0
					],
					[
						102000,
						4,
						0
					],
					[
						102107.142857143,
						6,
						0
					],
					[
						102214.285714286,
						5,
						0
					],
					[
						102214.285714286,
						1,
						0
					],
					[
						102321.428571429,
						2,
						107.142857142857
					],
					[
						102321.428571429,
						6,
						107.142857142857
					],
					[
						102535.714285714,
						5,
						0
					],
					[
						102642.857142857,
						4,
						0
					],
					[
						102535.714285714,
						1,
						0
					],
					[
						102642.857142857,
						0,
						0
					],
					[
						102750,
						2,
						107.142857142857
					],
					[
						102750,
						6,
						107.142857142857
					],
					[
						101214.285714286,
						2,
						0
					],
					[
						101214.285714286,
						6,
						0
					],
					[
						101642.857142857,
						0,
						0
					],
					[
						101642.857142857,
						4,
						0
					],
					[
						102285.714285714,
						0,
						0
					],
					[
						102285.714285714,
						4,
						0
					]
				],
				"mustHitSection": true
			},
			{
				"lengthInSteps": 16,
				"sectionNotes": [],
				"mustHitSection": false
			},
			{
				"lengthInSteps": 16,
				"sectionNotes": [],
				"mustHitSection": true
			},
			{
				"lengthInSteps": 16,
				"sectionNotes": [],
				"mustHitSection": true
			},
			{
				"lengthInSteps": 16,
				"sectionNotes": [],
				"mustHitSection": true
			},
			{
				"sectionBeats": 4,
				"sectionNotes": [],
				"typeOfSection": 0,
				"gfSection": false,
				"altAnim": false,
				"mustHitSection": true,
				"changeBPM": false,
				"bpm": 150
			},
			{
				"sectionBeats": 4,
				"sectionNotes": [],
				"typeOfSection": 0,
				"gfSection": false,
				"altAnim": false,
				"mustHitSection": true,
				"changeBPM": false,
				"bpm": 140
			},
			{
				"sectionBeats": 4,
				"sectionNotes": [],
				"typeOfSection": 0,
				"gfSection": false,
				"altAnim": false,
				"mustHitSection": true,
				"changeBPM": false,
				"bpm": 140
			},
			{
				"sectionBeats": 4,
				"sectionNotes": [],
				"typeOfSection": 0,
				"gfSection": false,
				"altAnim": false,
				"mustHitSection": true,
				"changeBPM": false,
				"bpm": 140
			},
			{
				"gfSection": false,
				"altAnim": false,
				"typeOfSection": 0,
				"sectionNotes": [],
				"bpm": 140,
				"sectionBeats": 4,
				"changeBPM": false,
				"mustHitSection": true
			}
		],
		"gfVersion": "gf",
		"events": [],
		"player3": null,
		"song": "Plumber Racer",
		"validScore": true,
		"needsVoices": true,
		"stage": "hive",
		"speed": 2.6,
		"bpm": 140
	}
}